{
	"nameShort": "eShell",
	"nameLong": "eShell",
	"applicationName": "eShell",
	"dataFolderName": ".eShell",
	"win32MutexName": "eshell",
	"licenseName": "MIT",
	"licenseUrl": "https://github.com/hernad/eShell/blob/master/LICENSE.txt",
	"win32AppId": "{{A34003BB-9E10-4501-8C11-BE3FAA83F201}",
	"win32x64AppId": "{{F77B7E06-80BA-4137-BCF4-654B95CCEB02}",
	"win32UserAppId": "{{F6065F05-9603-4FC4-8101-B9781A25D803}",
	"win32x64UserAppId": "{{F6065F05-9603-4FC4-8101-B9781A25D804}",
	"darwinBundleIdentifier": "ba.out.bring.eshell",
	"linuxIconName": "ba.out.bring.eshell",
	"licenseFileName": "LICENSE.txt",
	"reportIssueUrl": "https://github.com/hernad/eShell/issues/new",
	"keyboardShortcutsUrlLinux" : "https://code.visualstudio.com/shortcuts/keyboard-shortcuts-linux.pdf",
	"extensionAllowedProposedApi": [
		"ms-vscode.references-view"
	],
	"extensionsGallery": {
		"serviceUrl": "https://marketplace.visualstudio.com/_apis/public/gallery",
		"cacheUrl": "https://vscode.blob.core.windows.net/gallery/index",
		"itemUrl": "https://marketplace.visualstudio.com/items"
	},
	"win32DirName": "eShell",
	"win32NameVersion": "eShell",
	"win32RegValueName": "eShell",
	"win32AppUserModelId": "bringout.eShell",
	"win32ShellNameShort": "e&Shell",
	"urlProtocol": "vscode"
}
